mult.vhd
library ieee;
use ieee.std_logic_1164.all;
use ieee.numeric_std.all;

entity Multiplier32Bits is
    port(
        CLK: in std_logic;
        operand1,operand2: in signed(31 downto 0);
        mult_result: out signed(63 downto 0)
    );
end Multiplier32Bits;

architecture Behavioral of Multiplier32Bits is
signal temporal: signed(63 downto 0);

begin

    mult_process: process(CLK,temporal)
    begin
        if(rising_edge(clk)) then
    --Combinational part
            temporal <= (operand1*operand2);
    --Output assigment
            mult_result <= temporal;
        end if;
    end process mult_process;

end Behavioral;

sum/sumador.vhd
library ieee;
use ieee.std_logic_1164.all;
use ieee.numeric_std.all;

entity full_adder is
    generic(
       N         : integer := 32);
    port (
        clk      : in  std_logic;
        operand1 : in  signed(N-1 downto 0);
        operand2 : in  signed(N-1 downto 0);
        carry    : out  std_logic;
        add_result   : out signed(N-1 downto 0));
end;

architecture behavioral of full_adder is
    signal temporal     : signed (N downto 0);
    
    begin

    sum_process : process(clk)
    begin

        if(rising_edge(clk)) then
            --signal_op1 <= resize(signed(signal_op1),N);
            --signal_op2 <= resize(signed(signal_op2),N);
            --result <= std_logic_vector(signal_result);
            temporal <= ('0' & operand1) + ('0' & operand2);
            carry <= temporal(32);
            add_result <= temporal(31 downto 0);

        end if;
   end process sum_process; 
end;

main.vhd
library ieee;
use ieee.std_logic_1164.all;
use ieee.numeric_std.all;

entity runge_kutta_algorith is
    generic(
       N         : integer := 32);
    port (
        clk      : in  std_logic;
        operand1 : in  signed(N-1 downto 0);
        operand2 : in  signed(N-1 downto 0);
        operand3 : in  signed(N-1 downto 0);
        operand4 : in  signed(N-1 downto 0);
        result_alg   : out signed(2*N-1 downto 0));
end;

architecture structural of runge_kutta_algorith is

signal signal_in0 : std_logic_vector(N-1 downto 0);
signal signal_in1 : std_logic_vector(N-1 downto 0);
signal signal_out : std_logic_vector(N-1 downto 0);

component full_adder is
    port(
        clk      : in  std_logic;
        operand1 : in  signed(N-1 downto 0);
        operand2 : in  signed(N-1 downto 0);
        carry    : out  std_logic;
        add_result   : out signed(N-1 downto 0)
    );
end component;


component Multiplier32Bits is
    port(
        CLK: in std_logic;
        operand1,operand2: in signed(31 downto 0);
        mult_result: out signed(63 downto 0)
    );
end component;

signal signal_carry: std_logic;
signal signal_sum: signed(31 downto 0);
signal signal_mult: signed(63 downto 0);
signal signal_temporal     : signed (63 downto 0);

begin
  sum: full_adder port map (clk => clk, operand1 => operand1,operand2 => operand2, carry => signal_carry,add_result => signal_sum);
  mult: Multiplier32Bits port map (CLK => clk, operand1 => operand3,operand2 => operand4,mult_result => signal_mult);


    main_process : process(clk)
    begin

        if(rising_edge(clk)) then
            signal_temporal <= signal_sum + signal_mult;
            result_alg <= signal_temporal;

        end if;
   end process main_process; 

end architecture;

main_tb.vhd
library ieee;
use ieee.std_logic_1164.all;
use ieee.numeric_std.all;

entity runge_kutta_algorith_testbench is
end runge_kutta_algorith_testbench;

architecture behavior of runge_kutta_algorith_testbench is
    component runge_kutta_algorith is
    generic(
       N         : integer := 32);
        port (
        clk      : in  std_logic;
        operand1 : in  signed(N-1 downto 0);
        operand2 : in  signed(N-1 downto 0);
        operand3 : in  signed(N-1 downto 0);
        operand4 : in  signed(N-1 downto 0);
        result_alg   : out signed(2*N-1 downto 0));
    end component;
    signal signal_clk     : std_logic;
    signal signal_op1     : signed (31 downto 0);
    signal signal_op2     : signed (31 downto 0);
    signal signal_op3     : signed (31 downto 0);
    signal signal_op4     : signed (31 downto 0);
    signal signal_result  : signed (63 downto 0);

    constant clk_period : time := 10 ns;
begin
    uut: runge_kutta_algorith port map (
        clk      => signal_clk,
        operand1 => signal_op1,
        operand2 => signal_op2,
        operand3 => signal_op3,
        operand4 => signal_op4,
        result_alg   => signal_result
    );

   -- Clock process definitions
   Clk_process :process
   begin
        signal_clk <= '0';
        wait for clk_period/2;
        signal_clk <= '1';
        wait for clk_period/2;
   end process;

    stim_proc: process
    begin
        wait until rising_edge(signal_clk);
        wait for 20 ns;
        signal_op1 <= "00000000000000000000000000000001";
        signal_op2 <= "00000000000000000000000000000000";
        signal_op3 <= "00000000000000000000000000000001";
        signal_op4 <= "00000000000000000000000000000001";
        wait for 10 ns;
        signal_op1 <= "00000000000000000000000000000001";
        signal_op2 <= "00000000000000000000000000000001";
        signal_op3 <= "00000000000000000000000000000001";
        signal_op4 <= "00000000000000000000000000000001";
        wait for 10 ns;
        signal_op1 <= "00000000000000000000000000000001";
        signal_op2 <= "00000000000000000000000000000010";
        signal_op3 <= "00000000000000000000000000000001";
        signal_op4 <= "00000000000000000000000000000001";
        wait for 10 ns;
        signal_op1 <= "00000000000000000000000000000010";
        signal_op2 <= "00000000000000000000000000000010";
        signal_op3 <= "00000000000000000000000000000001";
        signal_op4 <= "00000000000000000000000000000001";
        report "Runge Kutta testbench finished";
        wait;
    end process;
end;

runge_kutta_algorith_testbench.vcd
$date
  Sun Jan  2 13:21:26 2022
$end
$version
  GHDL v0
$end
$timescale
  1 fs
$end
$scope module standard $end
$upscope $end
$scope module std_logic_1164 $end
$upscope $end
$scope module numeric_std $end
$upscope $end
$scope module runge_kutta_algorith_testbench $end
$var reg 1 ! signal_clk $end
$var reg 32 " signal_op1[31:0] $end
$var reg 32 # signal_op2[31:0] $end
$var reg 32 $ signal_op3[31:0] $end
$var reg 32 % signal_op4[31:0] $end
$var reg 64 & signal_result[63:0] $end
$scope module uut $end
$var reg 1 ' clk $end
$var reg 32 ( operand1[31:0] $end
$var reg 32 ) operand2[31:0] $end
$var reg 32 * operand3[31:0] $end
$var reg 32 + operand4[31:0] $end
$var reg 64 , result_alg[63:0] $end
$var reg 32 - signal_in0[31:0] $end
$var reg 32 . signal_in1[31:0] $end
$var reg 32 / signal_out[31:0] $end
$var reg 1 0 signal_carry $end
$var reg 32 1 signal_sum[31:0] $end
$var reg 64 2 signal_mult[63:0] $end
$var reg 64 3 signal_temporal[63:0] $end
$scope module sum $end
$var reg 1 4 clk $end
$var reg 32 5 operand1[31:0] $end
$var reg 32 6 operand2[31:0] $end
$var reg 1 7 carry $end
$var reg 32 8 add_result[31:0] $end
$var reg 33 9 temporal[32:0] $end
$upscope $end
$scope module mult $end
$var reg 1 : clk $end
$var reg 32 ; operand1[31:0] $end
$var reg 32 < operand2[31:0] $end
$var reg 64 = mult_result[63:0] $end
$var reg 64 > temporal[63:0] $end
$upscope $end
$upscope $end
$upscope $end
$enddefinitions $end
#0
0!
bUUUUUUUUUUUUUUUUUUUUUUUUUUUUUUUU "
bUUUUUUUUUUUUUUUUUUUUUUUUUUUUUUUU #
bUUUUUUUUUUUUUUUUUUUUUUUUUUUUUUUU $
bUUUUUUUUUUUUUUUUUUUUUUUUUUUUUUUU %
bUUUUUUUUUUUUUUUUUUUUUUUUUUUUUUUUUUUUUUUUUUUUUUUUUUUUUUUUUUUUUUUU &
0'
bUUUUUUUUUUUUUUUUUUUUUUUUUUUUUUUU (
bUUUUUUUUUUUUUUUUUUUUUUUUUUUUUUUU )
bUUUUUUUUUUUUUUUUUUUUUUUUUUUUUUUU *
bUUUUUUUUUUUUUUUUUUUUUUUUUUUUUUUU +
bUUUUUUUUUUUUUUUUUUUUUUUUUUUUUUUUUUUUUUUUUUUUUUUUUUUUUUUUUUUUUUUU ,
bUUUUUUUUUUUUUUUUUUUUUUUUUUUUUUUU -
bUUUUUUUUUUUUUUUUUUUUUUUUUUUUUUUU .
bUUUUUUUUUUUUUUUUUUUUUUUUUUUUUUUU /
U0
bUUUUUUUUUUUUUUUUUUUUUUUUUUUUUUUU 1
bUUUUUUUUUUUUUUUUUUUUUUUUUUUUUUUUUUUUUUUUUUUUUUUUUUUUUUUUUUUUUUUU 2
bUUUUUUUUUUUUUUUUUUUUUUUUUUUUUUUUUUUUUUUUUUUUUUUUUUUUUUUUUUUUUUUU 3
04
bUUUUUUUUUUUUUUUUUUUUUUUUUUUUUUUU 5
bUUUUUUUUUUUUUUUUUUUUUUUUUUUUUUUU 6
U7
bUUUUUUUUUUUUUUUUUUUUUUUUUUUUUUUU 8
bUUUUUUUUUUUUUUUUUUUUUUUUUUUUUUUUU 9
0:
bUUUUUUUUUUUUUUUUUUUUUUUUUUUUUUUU ;
bUUUUUUUUUUUUUUUUUUUUUUUUUUUUUUUU <
bUUUUUUUUUUUUUUUUUUUUUUUUUUUUUUUUUUUUUUUUUUUUUUUUUUUUUUUUUUUUUUUU =
bUUUUUUUUUUUUUUUUUUUUUUUUUUUUUUUUUUUUUUUUUUUUUUUUUUUUUUUUUUUUUUUU >
#5000000
1!
1'
bXXXXXXXXXXXXXXXXXXXXXXXXXXXXXXXXXXXXXXXXXXXXXXXXXXXXXXXXXXXXXXXX 3
14
bXXXXXXXXXXXXXXXXXXXXXXXXXXXXXXXXX 9
1:
bXXXXXXXXXXXXXXXXXXXXXXXXXXXXXXXXXXXXXXXXXXXXXXXXXXXXXXXXXXXXXXXX >
#10000000
0!
0'
04
0:
#15000000
1!
bXXXXXXXXXXXXXXXXXXXXXXXXXXXXXXXXXXXXXXXXXXXXXXXXXXXXXXXXXXXXXXXX &
1'
bXXXXXXXXXXXXXXXXXXXXXXXXXXXXXXXXXXXXXXXXXXXXXXXXXXXXXXXXXXXXXXXX ,
X0
bXXXXXXXXXXXXXXXXXXXXXXXXXXXXXXXX 1
bXXXXXXXXXXXXXXXXXXXXXXXXXXXXXXXXXXXXXXXXXXXXXXXXXXXXXXXXXXXXXXXX 2
14
X7
bXXXXXXXXXXXXXXXXXXXXXXXXXXXXXXXX 8
1:
bXXXXXXXXXXXXXXXXXXXXXXXXXXXXXXXXXXXXXXXXXXXXXXXXXXXXXXXXXXXXXXXX =
#20000000
0!
0'
04
0:
#25000000
1!
b00000000000000000000000000000001 "
b00000000000000000000000000000000 #
b00000000000000000000000000000001 $
b00000000000000000000000000000001 %
1'
b00000000000000000000000000000001 (
b00000000000000000000000000000000 )
b00000000000000000000000000000001 *
b00000000000000000000000000000001 +
14
b00000000000000000000000000000001 5
b00000000000000000000000000000000 6
b000000000000000000000000000000001 9
1:
b00000000000000000000000000000001 ;
b00000000000000000000000000000001 <
b0000000000000000000000000000000000000000000000000000000000000001 >
#30000000
0!
0'
04
0:
#35000000
1!
b00000000000000000000000000000001 #
1'
b00000000000000000000000000000001 )
00
b00000000000000000000000000000001 1
b0000000000000000000000000000000000000000000000000000000000000001 2
14
b00000000000000000000000000000001 6
07
b00000000000000000000000000000001 8
b000000000000000000000000000000010 9
1:
b0000000000000000000000000000000000000000000000000000000000000001 =
#40000000
0!
0'
04
0:
#45000000
1!
b00000000000000000000000000000010 #
1'
b00000000000000000000000000000010 )
b00000000000000000000000000000010 1
b0000000000000000000000000000000000000000000000000000000000000010 3
14
b00000000000000000000000000000010 6
b00000000000000000000000000000010 8
b000000000000000000000000000000011 9
1:
#50000000
0!
0'
04
0:
#55000000
1!
b00000000000000000000000000000010 "
b0000000000000000000000000000000000000000000000000000000000000010 &
1'
b00000000000000000000000000000010 (
b0000000000000000000000000000000000000000000000000000000000000010 ,
b00000000000000000000000000000011 1
b0000000000000000000000000000000000000000000000000000000000000011 3
14
b00000000000000000000000000000010 5
b00000000000000000000000000000011 8
b000000000000000000000000000000100 9
1:
#60000000
0!
0'
04
0:
#65000000
1!
b0000000000000000000000000000000000000000000000000000000000000011 &
1'
b0000000000000000000000000000000000000000000000000000000000000011 ,
b00000000000000000000000000000100 1
b0000000000000000000000000000000000000000000000000000000000000100 3
14
b00000000000000000000000000000100 8
1:
#70000000
0!
0'
04
0:
#75000000
1!
b0000000000000000000000000000000000000000000000000000000000000100 &
1'
b0000000000000000000000000000000000000000000000000000000000000100 ,
b0000000000000000000000000000000000000000000000000000000000000101 3
14
1:
#80000000
0!
0'
04
0:
#85000000
1!
b0000000000000000000000000000000000000000000000000000000000000101 &
1'
b0000000000000000000000000000000000000000000000000000000000000101 ,
14
1:
