mult.vhd
library ieee;
use ieee.std_logic_1164.all;
use ieee.numeric_std.all;

entity Multiplier32Bits is
    port(
        CLK: in std_logic;
        A,B: in signed(31 downto 0);
        R: out signed(31 downto 0)
    );
end Multiplier32Bits;

architecture Behavioral of Multiplier32Bits is
signal next_state: signed(63 downto 0);
signal state: signed(31 downto 0);

begin

    Sequential: process(CLK,state,next_state)
    begin
        if CLK'event and CLK = '1' then
            state <= next_state(61 downto 30);
        else
            state <= state;
        end if;
    end process Sequential;

    --Combinational part
        next_state <= (A*B);

    --Output assigment
    R <= state;

end Behavioral;

tmp/sumador.vhd
library ieee;
use ieee.std_logic_1164.all;
use ieee.numeric_std.all;

entity full_adder is
    generic(
       N         : integer := 32);
    port (
        clk      : in  std_logic;
        operand1 : in  signed(N-1 downto 0);
        operand2 : in  signed(N-1 downto 0);
        carry    : out  std_logic;
        result   : out signed(N-1 downto 0));
end;

architecture behavioral of full_adder is
    signal temporal     : signed (N downto 0);
    
    begin

    r_process : process(clk)
    begin

        if(rising_edge(clk)) then
            --signal_op1 <= resize(signed(signal_op1),N);
            --signal_op2 <= resize(signed(signal_op2),N);
            --result <= std_logic_vector(signal_result);
            temporal <= ('0' & operand1) + ('0' & operand2);
            carry <= temporal(32);
            result <= temporal(31 downto 0);

        end if;
   end process r_process; 
end;

main.vhd
library ieee;
use ieee.std_logic_1164.all;
use ieee.numeric_std.all;

entity runge_kutta_algorith is
    generic(
       N         : integer := 32);
    port (
        clk      : in  std_logic;
        operand1 : in  signed(N-1 downto 0);
        operand2 : in  signed(N-1 downto 0);
        result_alg   : out signed(N-1 downto 0));
end;

architecture structural of runge_kutta_algorith is

signal signal_in0 : std_logic_vector(N-1 downto 0);
signal signal_in1 : std_logic_vector(N-1 downto 0);
signal signal_out : std_logic_vector(N-1 downto 0);

component full_adder is
    port(
        clk      : in  std_logic;
        operand1 : in  signed(N-1 downto 0);
        operand2 : in  signed(N-1 downto 0);
        carry    : out  std_logic;
        result   : out signed(N-1 downto 0)
    );
end component;


component Multiplier32Bits is
    port(
        CLK: in std_logic;
        A,B: in signed(31 downto 0);
        R: out signed(31 downto 0)
    );
end component;

signal signal_carry: std_logic;
signal signal_sum: signed(31 downto 0);
signal signal_mult: signed(31 downto 0);
signal signal_temporal     : signed (31 downto 0);

begin
  sum: full_adder port map (clk => clk, operand1 => operand1,operand2 => operand2, carry => signal_carry,result => signal_sum);
  mult: Multiplier32Bits port map (CLK => clk, A => operand1,B => operand2,R => signal_mult);


    main_process : process(clk)
    begin

        if(rising_edge(clk)) then
            signal_temporal <= signal_sum + signal_mult;
            result_alg <= signal_temporal;

        end if;
   end process main_process; 

end architecture;

main_tb.vhd
library ieee;
use ieee.std_logic_1164.all;
use ieee.numeric_std.all;

entity runge_kutta_algorith_testbench is
end runge_kutta_algorith_testbench;

architecture behavior of runge_kutta_algorith_testbench is
    component runge_kutta_algorith is
    generic(
       N         : integer := 32);
        port (
        clk      : in  std_logic;
        operand1 : in  signed(N-1 downto 0);
        operand2 : in  signed(N-1 downto 0);
        result_alg   : out signed(N-1 downto 0));
    end component;
    signal signal_clk     : std_logic;
    signal signal_op1     : signed (31 downto 0);
    signal signal_op2     : signed (31 downto 0);
    signal signal_result  : signed (31 downto 0);

    constant clk_period : time := 10 ns;
begin
    uut: runge_kutta_algorith port map (
        clk      => signal_clk,
        operand1 => signal_op1,
        operand2 => signal_op2,
        result_alg   => signal_result
    );

   -- Clock process definitions
   Clk_process :process
   begin
        signal_clk <= '0';
        wait for clk_period/2;
        signal_clk <= '1';
        wait for clk_period/2;
   end process;

    stim_proc: process
    begin
        wait until rising_edge(signal_clk);
        wait for 20 ns;
        signal_op1 <= "00000000000000000000000000000001";
        signal_op2 <= "00000000000000000000000000000000";
        wait for 10 ns;
        signal_op1 <= "00000000000000000000000000000001";
        signal_op2 <= "00000000000000000000000000000001";
        wait for 10 ns;
        signal_op1 <= "00000000000000000000000000000001";
        signal_op2 <= "00000000000000000000000000000010";
        wait for 10 ns;
        signal_op1 <= "00000000000000000000000000000010";
        signal_op2 <= "00000000000000000000000000000010";
        report "Runge Kutta testbench finished";
        wait;
    end process;
end;

runge_kutta_algorith_testbench.vcd
$date
  Sat Jan  1 22:28:30 2022
$end
$version
  GHDL v0
$end
$timescale
  1 fs
$end
$scope module standard $end
$upscope $end
$scope module std_logic_1164 $end
$upscope $end
$scope module numeric_std $end
$upscope $end
$scope module runge_kutta_algorith_testbench $end
$var reg 1 ! signal_clk $end
$var reg 32 " signal_op1[31:0] $end
$var reg 32 # signal_op2[31:0] $end
$var reg 32 $ signal_result[31:0] $end
$scope module uut $end
$var reg 1 % clk $end
$var reg 32 & operand1[31:0] $end
$var reg 32 ' operand2[31:0] $end
$var reg 32 ( result_alg[31:0] $end
$var reg 32 ) signal_in0[31:0] $end
$var reg 32 * signal_in1[31:0] $end
$var reg 32 + signal_out[31:0] $end
$var reg 1 , signal_carry $end
$var reg 32 - signal_sum[31:0] $end
$var reg 32 . signal_mult[31:0] $end
$var reg 32 / signal_temporal[31:0] $end
$scope module sum $end
$var reg 1 0 clk $end
$var reg 32 1 operand1[31:0] $end
$var reg 32 2 operand2[31:0] $end
$var reg 1 3 carry $end
$var reg 32 4 result[31:0] $end
$var reg 33 5 temporal[32:0] $end
$upscope $end
$scope module mult $end
$var reg 1 6 clk $end
$var reg 32 7 a[31:0] $end
$var reg 32 8 b[31:0] $end
$var reg 32 9 r[31:0] $end
$var reg 64 : next_state[63:0] $end
$var reg 32 ; state[31:0] $end
$upscope $end
$upscope $end
$upscope $end
$enddefinitions $end
#0
0!
bUUUUUUUUUUUUUUUUUUUUUUUUUUUUUUUU "
bUUUUUUUUUUUUUUUUUUUUUUUUUUUUUUUU #
bUUUUUUUUUUUUUUUUUUUUUUUUUUUUUUUU $
0%
bUUUUUUUUUUUUUUUUUUUUUUUUUUUUUUUU &
bUUUUUUUUUUUUUUUUUUUUUUUUUUUUUUUU '
bUUUUUUUUUUUUUUUUUUUUUUUUUUUUUUUU (
bUUUUUUUUUUUUUUUUUUUUUUUUUUUUUUUU )
bUUUUUUUUUUUUUUUUUUUUUUUUUUUUUUUU *
bUUUUUUUUUUUUUUUUUUUUUUUUUUUUUUUU +
U,
bUUUUUUUUUUUUUUUUUUUUUUUUUUUUUUUU -
bUUUUUUUUUUUUUUUUUUUUUUUUUUUUUUUU .
bUUUUUUUUUUUUUUUUUUUUUUUUUUUUUUUU /
00
bUUUUUUUUUUUUUUUUUUUUUUUUUUUUUUUU 1
bUUUUUUUUUUUUUUUUUUUUUUUUUUUUUUUU 2
U3
bUUUUUUUUUUUUUUUUUUUUUUUUUUUUUUUU 4
bUUUUUUUUUUUUUUUUUUUUUUUUUUUUUUUUU 5
06
bUUUUUUUUUUUUUUUUUUUUUUUUUUUUUUUU 7
bUUUUUUUUUUUUUUUUUUUUUUUUUUUUUUUU 8
bUUUUUUUUUUUUUUUUUUUUUUUUUUUUUUUU 9
bXXXXXXXXXXXXXXXXXXXXXXXXXXXXXXXXXXXXXXXXXXXXXXXXXXXXXXXXXXXXXXXX :
bUUUUUUUUUUUUUUUUUUUUUUUUUUUUUUUU ;
#5000000
1!
1%
bXXXXXXXXXXXXXXXXXXXXXXXXXXXXXXXX .
bXXXXXXXXXXXXXXXXXXXXXXXXXXXXXXXX /
10
bXXXXXXXXXXXXXXXXXXXXXXXXXXXXXXXXX 5
16
bXXXXXXXXXXXXXXXXXXXXXXXXXXXXXXXX 9
bXXXXXXXXXXXXXXXXXXXXXXXXXXXXXXXX ;
#10000000
0!
0%
00
06
#15000000
1!
bXXXXXXXXXXXXXXXXXXXXXXXXXXXXXXXX $
1%
bXXXXXXXXXXXXXXXXXXXXXXXXXXXXXXXX (
X,
bXXXXXXXXXXXXXXXXXXXXXXXXXXXXXXXX -
10
X3
bXXXXXXXXXXXXXXXXXXXXXXXXXXXXXXXX 4
16
#20000000
0!
0%
00
06
#25000000
1!
b00000000000000000000000000000001 "
b00000000000000000000000000000000 #
1%
b00000000000000000000000000000001 &
b00000000000000000000000000000000 '
10
b00000000000000000000000000000001 1
b00000000000000000000000000000000 2
b000000000000000000000000000000001 5
16
b00000000000000000000000000000001 7
b00000000000000000000000000000000 8
b0000000000000000000000000000000000000000000000000000000000000000 :
#30000000
0!
0%
00
06
#35000000
1!
b00000000000000000000000000000001 #
1%
b00000000000000000000000000000001 '
0,
b00000000000000000000000000000001 -
b00000000000000000000000000000000 .
10
b00000000000000000000000000000001 2
03
b00000000000000000000000000000001 4
b000000000000000000000000000000010 5
16
b00000000000000000000000000000001 8
b00000000000000000000000000000000 9
b0000000000000000000000000000000000000000000000000000000000000001 :
b00000000000000000000000000000000 ;
#40000000
0!
0%
00
06
#45000000
1!
b00000000000000000000000000000010 #
1%
b00000000000000000000000000000010 '
b00000000000000000000000000000010 -
b00000000000000000000000000000001 /
10
b00000000000000000000000000000010 2
b00000000000000000000000000000010 4
b000000000000000000000000000000011 5
16
b00000000000000000000000000000010 8
b0000000000000000000000000000000000000000000000000000000000000010 :
#50000000
0!
0%
00
06
#55000000
1!
b00000000000000000000000000000010 "
b00000000000000000000000000000001 $
1%
b00000000000000000000000000000010 &
b00000000000000000000000000000001 (
b00000000000000000000000000000011 -
b00000000000000000000000000000010 /
10
b00000000000000000000000000000010 1
b00000000000000000000000000000011 4
b000000000000000000000000000000100 5
16
b00000000000000000000000000000010 7
b0000000000000000000000000000000000000000000000000000000000000100 :
#60000000
0!
0%
00
06
#65000000
1!
b00000000000000000000000000000010 $
1%
b00000000000000000000000000000010 (
b00000000000000000000000000000100 -
b00000000000000000000000000000011 /
10
b00000000000000000000000000000100 4
16
#70000000
0!
0%
00
06
#75000000
1!
b00000000000000000000000000000011 $
1%
b00000000000000000000000000000011 (
b00000000000000000000000000000100 /
10
16
#80000000
0!
0%
00
06
#85000000
1!
b00000000000000000000000000000100 $
1%
b00000000000000000000000000000100 (
10
16
